regsnp-0.3.2.data/scripts/regsnp_intron.py
regsnp_intron/__init__.py
regsnp_intron/feature_calculator.py
regsnp_intron/regsnp_intron.py
regsnp_intron/settings/settings.json
regsnp_intron/utils/__init__.py
regsnp_intron/utils/snp.py
regsnp_intron/utils/vcf.py
regsnp-0.3.2.dist-info/METADATA
regsnp-0.3.2.dist-info/WHEEL
regsnp-0.3.2.dist-info/top_level.txt
regsnp-0.3.2.dist-info/RECORD
