Metadata-Version: 2.1
Name: regsnp
Version: 0.3.2
Summary: Predict disease-causing probability of human intronic SNVs.
Home-page: https://github.com/mmammel12/regSNP
Author: linhai, mamammel
Author-email: linhai@iupui.edu, mamammel@iu.edu
License: MIT
Platform: UNKNOWN
Classifier: Development Status :: 3 - Alpha
Classifier: License :: OSI Approved :: MIT License
Classifier: Programming Language :: Python :: 2.7
Classifier: Topic :: Scientific/Engineering :: Bio-Informatics
Requires-Dist: pandas (==0.17.1)
Requires-Dist: pysam (==0.15.2)
Requires-Dist: pymongo
